th_random_ua/th_random_ua.py
user_agent_gather-1.1.4.dist-info/LICENSE
user_agent_gather-1.1.4.dist-info/METADATA
user_agent_gather-1.1.4.dist-info/WHEEL
user_agent_gather-1.1.4.dist-info/top_level.txt
user_agent_gather-1.1.4.dist-info/RECORD
