Metadata-Version: 2.1
Name: user-agent-gather
Version: 1.1.4
Summary: 随机ua
Home-page: 
Author: wzr
Author-email: 3163450460@qq.com
License: MIT Licence
Platform: any
License-File: LICENSE
